{
  "identifier": "zarke1-Stereolab--Les_Aimies_Des_Memes",
  "title": "Stereolab - Les Aimies Des M\u00eames",
  "addeddate": "2024-11-29 12:11:46",
  "description": "Animation/Image Manipulation - Anglezarke-01",
  "archive_url": "https://archive.org/details/zarke1-Stereolab--Les_Aimies_Des_Memes",
  "download_url": "https://archive.org/download/zarke1-Stereolab--Les_Aimies_Des_Memes/Stereolab--Les_Aimies_Des_Memes.mp4",
  "filename": "Stereolab--Les_Aimies_Des_Memes.mp4",
  "format": "MPEG4",
  "size": "734544873",
  "duration": "235.14",
  "width": "1280",
  "height": "720",
  "resolution": "1280x720"
}