{
  "identifier": "zarke1-Abstract_634_b",
  "title": "Abstract_634_b [Please download AVI video for full effect]",
  "addeddate": "2025-12-06 15:06:30",
  "description": "<div>Video shown is an MP4 file created by archive.org - to get the actual intended glitched effect you will have to download the AVI (.avi) version from the DOWNLOAD OPTIONS page...</div><div>\u00a0A video by Zarke1, abstract/experimental.</div>",
  "archive_url": "https://archive.org/details/zarke1-Abstract_634_b",
  "download_url": "https://archive.org/download/zarke1-Abstract_634_b/Abstract_634_b.mp4",
  "filename": "Abstract_634_b.mp4",
  "format": "h.264",
  "size": "4756011",
  "duration": "54.96",
  "width": "768",
  "height": "480",
  "resolution": "768x480"
}